{"trial_id": "0", "hyperparameters": {"space": [{"class_name": "Int", "config": {"name": "neurons", "default": null, "conditions": [], "min_value": 1, "max_value": 300, "step": 5, "sampling": "linear"}}, {"class_name": "Choice", "config": {"name": "actv", "default": "relu", "conditions": [], "values": ["relu", "tanh", "sigmoid"], "ordered": false}}, {"class_name": "Choice", "config": {"name": "optimizer", "default": "adam", "conditions": [], "values": ["adam", "rmsprop", "sgd"], "ordered": false}}, {"class_name": "Float", "config": {"name": "learning_rate", "default": 1e-05, "conditions": [], "min_value": 1e-05, "max_value": 0.001, "step": 1e-05, "sampling": "linear"}}], "values": {"neurons": 56, "actv": "relu", "optimizer": "adam", "learning_rate": 0.0007500000000000001}}, "metrics": {"metrics": {"loss": {"direction": "min", "observations": [{"value": [0.2133028581738472], "step": 23}]}, "accuracy": {"direction": "max", "observations": [{"value": [0.8976151943206787], "step": 23}]}, "val_loss": {"direction": "min", "observations": [{"value": [0.23307254910469055], "step": 23}]}, "val_accuracy": {"direction": "max", "observations": [{"value": [0.8870765268802643], "step": 23}]}}}, "score": 0.8870765268802643, "best_step": 23, "status": "COMPLETED", "message": null}